README.md
setup.cfg
setup.py
makeit/__init__.py
makeit/core.py
makeit.egg-info/PKG-INFO
makeit.egg-info/SOURCES.txt
makeit.egg-info/dependency_links.txt
makeit.egg-info/requires.txt
makeit.egg-info/top_level.txt
makeit/contrib/__init__.py
makeit/contrib/graphviz.py
makeit/contrib/sqlitedict.py
makeit/contrib/tqdm.py
tests/__init__.py
tests/test_aio_execute.py
tests/test_aio_execution_flags.py
tests/test_calculator.py
tests/test_contrib_sqlitedict.py
tests/test_crash_during_execution.py
tests/test_dataclass_task.py
tests/test_execute_on_change.py
tests/test_execution_flags.py
tests/test_mp_big.py
tests/test_mp_exception.py
tests/test_mp_execute_on_change.py
tests/test_mp_execution_flags.py
tests/test_self_source.py
tests/test_strickt_executions.py
tests/test_with_backend.py
tests/utils.py