Metadata-Version: 2.1
Name: makeit
Version: 2.10.13
Summary: Make util for applications
Home-page: UNKNOWN
Author: Dmitrii Ushanov
Author-email: ushanov.dmitry@gmail.com
License: Public Domain
Platform: UNKNOWN
Classifier: Development Status :: 4 - Beta
Classifier: Intended Audience :: Developers
Classifier: License :: Public Domain
Classifier: Topic :: Software Development :: Libraries :: Application Frameworks
Classifier: Topic :: Utilities
Requires-Python: >=3.10
